<manifest
    xmlns="https://github.com/erasmus-without-paper/ewp-specs-api-discovery/tree/stable-v6"
    xmlns:d5="https://github.com/erasmus-without-paper/ewp-specs-api-discovery/blob/stable-v6/manifest-entry.xsd"
    xmlns:e2="https://github.com/erasmus-without-paper/ewp-specs-api-echo/blob/stable-v2/manifest-entry.xsd"
    xmlns:ewp="https://github.com/erasmus-without-paper/ewp-specs-architecture/blob/stable-v1/common-types.xsd"
    xmlns:f1="https://github.com/erasmus-without-paper/ewp-specs-api-factsheet/blob/stable-v1/manifest-entry.xsd"
    xmlns:ia6="https://github.com/erasmus-without-paper/ewp-specs-api-iias/blob/stable-v6/manifest-entry.xsd"
    xmlns:iaa1="https://github.com/erasmus-without-paper/ewp-specs-api-iias-approval/blob/stable-v1/manifest-entry.xsd"
    xmlns:iaac1="https://github.com/erasmus-without-paper/ewp-specs-api-iia-approval-cnr/blob/stable-v1/manifest-entry.xsd"
    xmlns:iac2="https://github.com/erasmus-without-paper/ewp-specs-api-iia-cnr/blob/stable-v2/manifest-entry.xsd"
    xmlns:in2="https://github.com/erasmus-without-paper/ewp-specs-api-institutions/blob/stable-v2/manifest-entry.xsd"
    xmlns:ou2="https://github.com/erasmus-without-paper/ewp-specs-api-ounits/blob/stable-v2/manifest-entry.xsd"
    xmlns:r="https://github.com/erasmus-without-paper/ewp-specs-api-registry/tree/stable-v1"
    xmlns:sec="https://github.com/erasmus-without-paper/ewp-specs-sec-intro/tree/stable-v2"
    xmlns:sec-A0="https://github.com/erasmus-without-paper/ewp-specs-sec-cliauth-none/tree/stable-v1"
    xmlns:sec-A1="https://github.com/erasmus-without-paper/ewp-specs-sec-cliauth-tlscert/tree/stable-v1"
    xmlns:sec-A2="https://github.com/erasmus-without-paper/ewp-specs-sec-cliauth-httpsig/tree/stable-v1"
    xmlns:sec-B1="https://github.com/erasmus-without-paper/ewp-specs-sec-srvauth-tlscert/tree/stable-v1"
    xmlns:sec-B2="https://github.com/erasmus-without-paper/ewp-specs-sec-srvauth-httpsig/tree/stable-v1"
    xmlns:sec-C1="https://github.com/erasmus-without-paper/ewp-specs-sec-reqencr-tls/tree/stable-v1"
    xmlns:sec-C2="https://github.com/erasmus-without-paper/ewp-specs-sec-resencr-tls/tree/stable-v1"
>
    <host>
        <ewp:admin-email>ewp@kion.com.tr</ewp:admin-email>
        <ewp:admin-provider>KION (EXCHANGER)</ewp:admin-provider>
        <ewp:admin-notes/>
        <r:apis-implemented>
            <d5:discovery version="6.0.0">
                <d5:url>https://ewp.kion.com.tr/api/manifest/karatay</d5:url>
            </d5:discovery>
            <e2:echo version="2.0.1">
                <e2:http-security>
                    <sec:client-auth-methods>
                        <sec-A2:httpsig/>
                    </sec:client-auth-methods>
                    <sec:server-auth-methods>
                        <sec-B2:httpsig/>
                    </sec:server-auth-methods>
                </e2:http-security>
                <e2:url>https://ewp.kion.com.tr/api/echo/karatay</e2:url>
            </e2:echo>
            <in2:institutions version="2.1.0">
                <in2:http-security>
                    <sec:client-auth-methods>
                        <sec-A2:httpsig/>
                    </sec:client-auth-methods>
                    <sec:server-auth-methods>
                        <sec-B2:httpsig/>
                    </sec:server-auth-methods>
                </in2:http-security>
                <in2:url>https://ewp.kion.com.tr/api/institutions/karatay</in2:url>
                <in2:max-hei-ids>10</in2:max-hei-ids>
            </in2:institutions>
            <ou2:organizational-units version="2.1.1">
                <ou2:http-security>
                    <sec:client-auth-methods>
                        <sec-A2:httpsig/>
                    </sec:client-auth-methods>
                    <sec:server-auth-methods>
                        <sec-B2:httpsig/>
                    </sec:server-auth-methods>
                </ou2:http-security>
                <ou2:url>https://ewp.kion.com.tr/api/organizationalunits/karatay</ou2:url>
                <ou2:max-ounit-ids>100</ou2:max-ounit-ids>
                <ou2:max-ounit-codes>100</ou2:max-ounit-codes>
            </ou2:organizational-units>
            <ia6:iias version="6.0.1">
                <ia6:http-security>
                    <sec:client-auth-methods>
                        <sec-A2:httpsig/>
                    </sec:client-auth-methods>
                    <sec:server-auth-methods>
                        <sec-B2:httpsig/>
                    </sec:server-auth-methods>
                </ia6:http-security>
                <ia6:get-url>https://ewp.kion.com.tr/api/interinstitutionalagreements/get/karatay</ia6:get-url>
                <ia6:max-iia-ids>1</ia6:max-iia-ids>
                <ia6:max-iia-codes>1</ia6:max-iia-codes>
                <ia6:index-url>https://ewp.kion.com.tr/api/interinstitutionalagreements/index/karatay</ia6:index-url>
            </ia6:iias>
            <iac2:iia-cnr version="2.0.3">
                <iac2:http-security>
                    <sec:client-auth-methods>
                        <sec-A2:httpsig/>
                    </sec:client-auth-methods>
                    <sec:server-auth-methods>
                        <sec-B2:httpsig/>
                    </sec:server-auth-methods>
                </iac2:http-security>
                <iac2:url>https://ewp.kion.com.tr/api/interinstitutionalagreements/cnr/karatay</iac2:url>
            </iac2:iia-cnr>
            <iaa1:iias-approval version="1.0.0">
                <iaa1:http-security>
                    <sec:client-auth-methods>
                        <sec-A2:httpsig/>
                    </sec:client-auth-methods>
                    <sec:server-auth-methods>
                        <sec-B2:httpsig/>
                    </sec:server-auth-methods>
                </iaa1:http-security>
                <iaa1:url>https://ewp.kion.com.tr/api/interinstitutionalagreements/approval/karatay</iaa1:url>
                <iaa1:max-iia-ids>1</iaa1:max-iia-ids>
            </iaa1:iias-approval>
            <iaac1:iia-approval-cnr version="1.0.0">
                <iaac1:http-security>
                    <sec:client-auth-methods>
                        <sec-A2:httpsig/>
                    </sec:client-auth-methods>
                    <sec:server-auth-methods>
                        <sec-B2:httpsig/>
                    </sec:server-auth-methods>
                </iaac1:http-security>
                <iaac1:url>https://ewp.kion.com.tr/api/interinstitutionalagreements/approval/cnr/karatay</iaac1:url>
            </iaac1:iia-approval-cnr>
            <f1:factsheet version="1.0.0">
                <f1:http-security>
                    <sec:client-auth-methods>
                        <sec-A2:httpsig/>
                    </sec:client-auth-methods>
                    <sec:server-auth-methods>
                        <sec-B2:httpsig/>
                    </sec:server-auth-methods>
                </f1:http-security>
                <f1:url>https://ewp.kion.com.tr/api/interinstitutionalagreements/factsheet/karatay</f1:url>
                <f1:max-hei-ids>25</f1:max-hei-ids>
            </f1:factsheet>
            <omobilities
                xmlns="https://github.com/erasmus-without-paper/ewp-specs-api-omobilities/blob/stable-v1/manifest-entry.xsd"
                version="1.0.0"
            >
                <http-security>
                    <sec:client-auth-methods>
                        <sec-A2:httpsig/>
                    </sec:client-auth-methods>
                    <sec:server-auth-methods>
                        <sec-B2:httpsig/>
                    </sec:server-auth-methods>
                </http-security>
                <get-url>https://ewp.kion.com.tr/api/outgoingmobilities/get/karatay</get-url>
                <index-url>https://ewp.kion.com.tr/api/outgoingmobilities/index/karatay</index-url>
                <max-omobility-ids>25</max-omobility-ids>
                <sends-notifications/>
            </omobilities>
            <omobility-cnr
                xmlns="https://github.com/erasmus-without-paper/ewp-specs-api-omobility-cnr/blob/stable-v1/manifest-entry.xsd"
                version="1.0.0"
            >
                <http-security>
                    <sec:client-auth-methods>
                        <sec-A2:httpsig/>
                    </sec:client-auth-methods>
                    <sec:server-auth-methods>
                        <sec-B2:httpsig/>
                    </sec:server-auth-methods>
                </http-security>
                <url>https://ewp.kion.com.tr/api/outgoingmobilities/cnr/karatay</url>
                <max-omobility-ids>25</max-omobility-ids>
            </omobility-cnr>
            <imobilities
                xmlns="https://github.com/erasmus-without-paper/ewp-specs-api-imobilities/blob/stable-v1/manifest-entry.xsd"
                version="1.0.0"
            >
                <http-security>
                    <sec:client-auth-methods>
                        <sec-A2:httpsig/>
                    </sec:client-auth-methods>
                    <sec:server-auth-methods>
                        <sec-B2:httpsig/>
                    </sec:server-auth-methods>
                </http-security>
                <get-url>https://ewp.kion.com.tr/api/incomingmobilities/get/karatay</get-url>
                <max-omobility-ids>25</max-omobility-ids>
                <sends-notifications/>
            </imobilities>
            <imobility-cnr
                xmlns="https://github.com/erasmus-without-paper/ewp-specs-api-imobility-cnr/blob/stable-v1/manifest-entry.xsd"
                version="1.0.0"
            >
                <http-security>
                    <sec:client-auth-methods>
                        <sec-A2:httpsig/>
                    </sec:client-auth-methods>
                    <sec:server-auth-methods>
                        <sec-B2:httpsig/>
                    </sec:server-auth-methods>
                </http-security>
                <url>https://ewp.kion.com.tr/api/incomingmobilities/cnr/karatay</url>
                <max-omobility-ids>25</max-omobility-ids>
            </imobility-cnr>
            <omobility-las
                xmlns="https://github.com/erasmus-without-paper/ewp-specs-api-omobility-las/blob/stable-v1/manifest-entry.xsd"
                version="1.0.1"
            >
                <http-security>
                    <sec:client-auth-methods>
                        <sec-A2:httpsig/>
                    </sec:client-auth-methods>
                    <sec:server-auth-methods>
                        <sec-B2:httpsig/>
                    </sec:server-auth-methods>
                </http-security>
                <get-url>https://ewp.kion.com.tr/api/outgoingmobilities/learning-agreement/get/karatay</get-url>
                <index-url>https://ewp.kion.com.tr/api/outgoingmobilities/learning-agreement/index/karatay</index-url>
                <update-url>https://ewp.kion.com.tr/api/outgoingmobilities/learning-agreement/update/karatay</update-url>
                <max-omobility-ids>1</max-omobility-ids>
            </omobility-las>
            <omobility-la-cnr
                xmlns="https://github.com/erasmus-without-paper/ewp-specs-api-omobility-la-cnr/blob/stable-v1/manifest-entry.xsd"
                version="1.0.0"
            >
                <http-security>
                    <sec:client-auth-methods>
                        <sec-A2:httpsig/>
                    </sec:client-auth-methods>
                    <sec:server-auth-methods>
                        <sec-B2:httpsig/>
                    </sec:server-auth-methods>
                </http-security>
                <url>https://ewp.kion.com.tr/api/outgoingmobilities/learning-agreement/cnr/karatay</url>
                <max-omobility-ids>1</max-omobility-ids>
            </omobility-la-cnr>
        </r:apis-implemented>
        <institutions-covered>
            <r:hei id="karatay.edu.tr">
                <r:other-id type="pic">946179032</r:other-id>
                <r:other-id type="erasmus">TR KONYA02</r:other-id>
                <r:name xml:lang="tr">KTO Karatay Üniversitesi</r:name>
                <r:name xml:lang="en">KTO Karatay University</r:name>
            </r:hei>
        </institutions-covered>
        <client-credentials-in-use>
            <certificate>MIID9TCCAt2gAwIBAgIUSa/MGmnalFuRup4PPZV/9ExU1KkwDQYJKoZIhvcNAQELBQAwgYgxCzAJ
BgNVBAYTAnRyMQ8wDQYDVQQIDAZ0dXJrZXkxETAPBgNVBAcMCGlzdGFuYnVsMQ0wCwYDVQQKDARr
aW9uMRIwEAYDVQQLDAlleGNoYW5nZXIxEjAQBgNVBAMMCWV4Y2hhbmdlcjEeMBwGCSqGSIb3DQEJ
ARYPZXdwQGtpb24uY29tLnRyMCAXDTIyMDcwNjEzMTgwOFoYDzIxMjIwNjEyMTMxODA4WjCBiDEL
MAkGA1UEBhMCdHIxDzANBgNVBAgMBnR1cmtleTERMA8GA1UEBwwIaXN0YW5idWwxDTALBgNVBAoM
BGtpb24xEjAQBgNVBAsMCWV4Y2hhbmdlcjESMBAGA1UEAwwJZXhjaGFuZ2VyMR4wHAYJKoZIhvcN
AQkBFg9ld3BAa2lvbi5jb20udHIwggEiMA0GCSqGSIb3DQEBAQUAA4IBDwAwggEKAoIBAQC2w0iO
LYq/nQqCRVGtVyvBct1FZc6fmSJMjaMa20ubxntTZdsY0PpKJTcy/ORWlStgX768qEMdQijtOS4e
lYDrT2nN64Nl1omMph7ki11omRcgEfDiBh6oJBgiiFwuwAJJigcgji9x+h0Sut9PzNXBG2laHiXQ
hihGphHz8itHFyt7+TXoqz1ApUsHRDJ6/5sgXeT1lWOD87LAB2HsusGLoLm3dZabNs7inuOYgnd2
m6ieXzG1qs4xGzAKsd7LwEnQVYFmBTFi3q+zf3G23Z7C+33hxU6gLg/JcwXkC+RlzUZsHIZHoztJ
fdUYcqdyZ/CTvoZFtSlSsc7/TOMSs7vTAgMBAAGjUzBRMB0GA1UdDgQWBBTzE8yndrsVJPUUvhWX
SNgB2buBcDAfBgNVHSMEGDAWgBTzE8yndrsVJPUUvhWXSNgB2buBcDAPBgNVHRMBAf8EBTADAQH/
MA0GCSqGSIb3DQEBCwUAA4IBAQAnU3vsVR3YbhVYHeC+s/T+SDaJsCbDcyooTeKEFLFzA1d4KY/L
BMzvYHULUyuNRGWP30aA5p8CvwqxgxU2xXv/JU2TRO35eEvUedpkVj3pQ85bDQKBPdweRcxyMGnh
0ppia/ERRgMhovrAiM+s0b0A/TCb1RNGagQUHVBuIofG6Lhv1ENZjXSql6WELCFsBX6bubLv4NY3
/GnbViTlsuKFOsV/q2Mjwhx1DnJumsy6bkER7AKQiiZaO6gON8mwDqUBtIy8nVIxda4JjtVFDExC
qZaME4hxP+JajaxQplguRredaRyo1a7jt6ZVKhWHWOBJeXICNWGeYRxYqjiRjJrD</certificate>
            <rsa-public-key>MIIBIjANBgkqhkiG9w0BAQEFAAOCAQ8AMIIBCgKCAQEAtsNIji2Kv50KgkVRrVcr
wXLdRWXOn5kiTI2jGttLm8Z7U2XbGND6SiU3MvzkVpUrYF++vKhDHUIo7TkuHpWA
609pzeuDZdaJjKYe5ItdaJkXIBHw4gYeqCQYIohcLsACSYoHII4vcfodErrfT8zV
wRtpWh4l0IYoRqYR8/IrRxcre/k16Ks9QKVLB0Qyev+bIF3k9ZVjg/OywAdh7LrB
i6C5t3WWmzbO4p7jmIJ3dpuonl8xtarOMRswCrHey8BJ0FWBZgUxYt6vs39xtt2e
wvt94cVOoC4PyXMF5AvkZc1GbByGR6M7SX3VGHKncmfwk76GRbUpUrHO/0zjErO7
0wIDAQAB</rsa-public-key>
        </client-credentials-in-use>
        <server-credentials-in-use>
            <rsa-public-key>MIIBIjANBgkqhkiG9w0BAQEFAAOCAQ8AMIIBCgKCAQEAtsNIji2Kv50KgkVRrVcr
wXLdRWXOn5kiTI2jGttLm8Z7U2XbGND6SiU3MvzkVpUrYF++vKhDHUIo7TkuHpWA
609pzeuDZdaJjKYe5ItdaJkXIBHw4gYeqCQYIohcLsACSYoHII4vcfodErrfT8zV
wRtpWh4l0IYoRqYR8/IrRxcre/k16Ks9QKVLB0Qyev+bIF3k9ZVjg/OywAdh7LrB
i6C5t3WWmzbO4p7jmIJ3dpuonl8xtarOMRswCrHey8BJ0FWBZgUxYt6vs39xtt2e
wvt94cVOoC4PyXMF5AvkZc1GbByGR6M7SX3VGHKncmfwk76GRbUpUrHO/0zjErO7
0wIDAQAB</rsa-public-key>
        </server-credentials-in-use>
    </host>
</manifest>
