<?xml version="1.0"?>
<ns1:manifest 
   xmlns:ns1="https://github.com/erasmus-without-paper/ewp-specs-api-discovery/tree/stable-v6" 
   xmlns="https://github.com/erasmus-without-paper/ewp-specs-architecture/blob/stable-v1/common-types.xsd" 
   xmlns:ns2="https://github.com/erasmus-without-paper/ewp-specs-api-registry/tree/stable-v1" 
   xmlns:d1="https://github.com/erasmus-without-paper/ewp-specs-api-discovery/blob/stable-v6/manifest-entry.xsd" 
   xmlns:e1="https://github.com/erasmus-without-paper/ewp-specs-api-echo/blob/stable-v2/manifest-entry.xsd" 
   xmlns:sec="https://github.com/erasmus-without-paper/ewp-specs-sec-intro/tree/stable-v2" 
   xmlns:sec_cc="https://github.com/erasmus-without-paper/ewp-specs-sec-cliauth-tlscert/tree/stable-v1" 
   xmlns:sec_cs="https://github.com/erasmus-without-paper/ewp-specs-sec-cliauth-httpsig/tree/stable-v1" 
   xmlns:sec_sc="https://github.com/erasmus-without-paper/ewp-specs-sec-srvauth-tlscert/tree/stable-v1" 
   xmlns:sec_ss="https://github.com/erasmus-without-paper/ewp-specs-sec-srvauth-httpsig/tree/stable-v1" 
   xmlns:in2="https://github.com/erasmus-without-paper/ewp-specs-api-institutions/blob/stable-v2/manifest-entry.xsd" 
   xmlns:out2="https://github.com/erasmus-without-paper/ewp-specs-api-ounits/blob/stable-v2/manifest-entry.xsd" 
   xmlns:iapc="https://github.com/erasmus-without-paper/ewp-specs-api-iia-approval-cnr/blob/stable-v2/manifest-entry.xsd" 
   xmlns:iaap="https://github.com/erasmus-without-paper/ewp-specs-api-iias-approval/blob/stable-v2/manifest-entry.xsd" 
   xmlns:ia2="https://github.com/erasmus-without-paper/ewp-specs-api-iias/blob/stable-v7/manifest-entry.xsd" 
   xmlns:iac2="https://github.com/erasmus-without-paper/ewp-specs-api-iia-cnr/blob/stable-v3/manifest-entry.xsd" 
   xmlns:iafs="https://github.com/erasmus-without-paper/ewp-specs-api-factsheet/blob/stable-v1/manifest-entry.xsd" 
   xmlns:om="https://github.com/erasmus-without-paper/ewp-specs-api-omobilities/blob/stable-v1/manifest-entry.xsd" 
   xmlns:omc="https://github.com/erasmus-without-paper/ewp-specs-api-omobility-cnr/blob/stable-v1/manifest-entry.xsd" 
   xmlns:oml="https://github.com/erasmus-without-paper/ewp-specs-api-omobility-las/blob/stable-v1/manifest-entry.xsd" 
   xmlns:omlc="https://github.com/erasmus-without-paper/ewp-specs-api-omobility-la-cnr/blob/stable-v1/manifest-entry.xsd">
  <ns1:host>
    <admin-email>admin-ewp@vut.cz</admin-email>
    <admin-provider>Brno University of Technology (Apollo)</admin-provider>
    <admin-notes>This is the production server.</admin-notes>
    <ns2:apis-implemented>
      <d1:discovery version="6.0.0">
        <d1:url>https://ewp-api.vut.cz/ewp/manifest.xml</d1:url>
      </d1:discovery>
      <e1:echo version="2.0.1">
        <e1:http-security>
          <sec:client-auth-methods>
            <sec_cs:httpsig/>
          </sec:client-auth-methods>
          <sec:server-auth-methods>
            <sec_sc:tlscert/>
            <sec_ss:httpsig/>
          </sec:server-auth-methods>
        </e1:http-security>
        <e1:url>https://ewp-api.vut.cz/ewp/api/echo</e1:url>
      </e1:echo>
      <in2:institutions version="2.2.0">
        <in2:http-security>
          <sec:client-auth-methods>
            <sec_cs:httpsig/>
          </sec:client-auth-methods>
          <sec:server-auth-methods>
            <sec_sc:tlscert/>
            <sec_ss:httpsig/>
          </sec:server-auth-methods>
        </in2:http-security>
        <in2:url>https://ewp-api.vut.cz/ewp/api/institutions</in2:url>
        <in2:max-hei-ids>1</in2:max-hei-ids>
      </in2:institutions>
      <ia2:iias version="7.0.0">
        <ia2:http-security>
          <sec:client-auth-methods>
            <sec_cs:httpsig/>
          </sec:client-auth-methods>
          <sec:server-auth-methods>
            <sec_sc:tlscert/>
            <sec_ss:httpsig/>
          </sec:server-auth-methods>
        </ia2:http-security>
        <ia2:get-url>https://ewp-api.vut.cz/ewp/api/iias/get</ia2:get-url>
        <ia2:max-iia-ids>10</ia2:max-iia-ids>
        <ia2:index-url>https://ewp-api.vut.cz/ewp/api/iias/index</ia2:index-url>
        <ia2:stats-url>https://ewp-api.vut.cz/ewp/api/iias/stats</ia2:stats-url>
      </ia2:iias>
      <iac2:iia-cnr version="3.0.0">
        <iac2:http-security>
          <sec:client-auth-methods>
            <sec_cs:httpsig/>
          </sec:client-auth-methods>
          <sec:server-auth-methods>
            <sec_sc:tlscert/>
            <sec_ss:httpsig/>
          </sec:server-auth-methods>
        </iac2:http-security>
        <iac2:url>https://ewp-api.vut.cz/ewp/api/iia-cnr</iac2:url>
      </iac2:iia-cnr>
      <iaap:iias-approval version="2.0.0">
        <iaap:http-security>
          <sec:client-auth-methods>
            <sec_cs:httpsig/>
          </sec:client-auth-methods>
          <sec:server-auth-methods>
            <sec_sc:tlscert/>
            <sec_ss:httpsig/>
          </sec:server-auth-methods>
        </iaap:http-security>
        <iaap:url>https://ewp-api.vut.cz/ewp/api/iias-approval</iaap:url>
        <iaap:max-iia-ids>20</iaap:max-iia-ids>
      </iaap:iias-approval>
      <iapc:iia-approval-cnr version="2.0.0">
        <iapc:http-security>
          <sec:client-auth-methods>
            <sec_cs:httpsig/>
          </sec:client-auth-methods>
          <sec:server-auth-methods>
            <sec_sc:tlscert/>
            <sec_ss:httpsig/>
          </sec:server-auth-methods>
        </iapc:http-security>
        <iapc:url>https://ewp-api.vut.cz/ewp/api/iia-approval-cnr</iapc:url>
      </iapc:iia-approval-cnr>
      <iafs:factsheet version="1.1.0">
        <iafs:http-security>
          <sec:client-auth-methods>
            <sec_cs:httpsig/>
          </sec:client-auth-methods>
          <sec:server-auth-methods>
            <sec_sc:tlscert/>
            <sec_ss:httpsig/>
          </sec:server-auth-methods>
        </iafs:http-security>
        <iafs:url>https://ewp-api.vut.cz/ewp/api/iia-factsheet</iafs:url>
        <iafs:max-hei-ids>1</iafs:max-hei-ids>
      </iafs:factsheet>
    </ns2:apis-implemented>
    <ns1:institutions-covered>
      <ns2:hei id="vutbr.cz">
        <ns2:other-id type="pic">999873091</ns2:other-id>
        <ns2:other-id type="erasmus">CZ BRNO01</ns2:other-id>
        <ns2:other-id type="erasmus-charter">49565-EPP-1-2014-1-CZ-EPPKA3-ECHE</ns2:other-id>
        <ns2:name xml:lang="cz">VYSOKÉ UČENÍ TECHNICKÉ V BRNĚ</ns2:name>
        <ns2:name xml:lang="en">BRNO UNIVERSITY OF TECHNOLOGY</ns2:name>
      </ns2:hei>
    </ns1:institutions-covered>
    <ns1:client-credentials-in-use>
      <ns1:certificate>MIIHaDCCBVCgAwIBAgIRANknDwkUHHlFFt9Jc8BrVbUwDQYJKoZIhvcNAQEMBQAw
RDELMAkGA1UEBhMCTkwxGTAXBgNVBAoTEEdFQU5UIFZlcmVuaWdpbmcxGjAYBgNV
BAMTEUdFQU5UIE9WIFJTQSBDQSA0MB4XDTI0MTAzMDAwMDAwMFoXDTI1MTAzMDIz
NTk1OVowczELMAkGA1UEBhMCQ1oxGzAZBgNVBAgMEkppaG9tb3JhdnNrw70ga3Jh
ajErMCkGA1UECgwiVnlzb2vDqSB1xI1lbsOtIHRlY2huaWNrw6kgdiBCcm7EmzEa
MBgGA1UEAxMRcGVydW4yMi5yby52dXQuY3owggEiMA0GCSqGSIb3DQEBAQUAA4IB
DwAwggEKAoIBAQC+FSsVrcfINKIsg122cBPBor7TIMG/9kmo91tyn/nnFfrUerIc
H81aWbqCoKbAgUFrHsnZ/eGGLie9AzGe5nHS4W98GUZMjtL1yTRzDuuKbxp+wOL3
37WMbGy6jBVI2aG20os36yAYcJ5QWfcwL2NcLSYNO0e42UxlnqxgJwEbfcLWwFGi
JLd19ycXBqwr12H73y75uEvqAoJtoAX/oRo1474w2IqgiFDFNhO0IrhfUs7hQ0AL
CabcM6ftLchaBZWdjRC2c/zw4Zw4EBgzl0EJHMQANJDmmeK+j16kcvFx2meSSJA2
DpKCxfZCLRBSCISstDYIxmzzzqGrMJp2wpv9AgMBAAGjggMkMIIDIDAfBgNVHSME
GDAWgBRvHTVJEGwy+lmgnryK6B+VvnF6DDAdBgNVHQ4EFgQUd/Uk5qicF8Nen3MT
0NEeO8lKmpowDgYDVR0PAQH/BAQDAgWgMAwGA1UdEwEB/wQCMAAwHQYDVR0lBBYw
FAYIKwYBBQUHAwEGCCsGAQUFBwMCMEkGA1UdIARCMEAwNAYLKwYBBAGyMQECAk8w
JTAjBggrBgEFBQcCARYXaHR0cHM6Ly9zZWN0aWdvLmNvbS9DUFMwCAYGZ4EMAQIC
MD8GA1UdHwQ4MDYwNKAyoDCGLmh0dHA6Ly9HRUFOVC5jcmwuc2VjdGlnby5jb20v
R0VBTlRPVlJTQUNBNC5jcmwwdQYIKwYBBQUHAQEEaTBnMDoGCCsGAQUFBzAChi5o
dHRwOi8vR0VBTlQuY3J0LnNlY3RpZ28uY29tL0dFQU5UT1ZSU0FDQTQuY3J0MCkG
CCsGAQUFBzABhh1odHRwOi8vR0VBTlQub2NzcC5zZWN0aWdvLmNvbTCCAX4GCisG
AQQB1nkCBAIEggFuBIIBagFoAHUA3dzKNJXX4RYF55Uy+sef+D0cUN/bADoUEnYK
LKy7yCoAAAGS3GrQXAAABAMARjBEAiAXUull1LpsGwzsGjm4raAbTeoqIDKS8tNF
Vg+F279ryQIgY6kowboer5c8ZGbw3M9qz2RE1/sLm+oUfAQDKZ+t0kkAdgDM+w9q
hXEJZf6Vm1PO6bJ8IumFXA2XjbapflTA/kwNsAAAAZLcatAgAAAEAwBHMEUCICYb
Q0tKs9nokTEiLjfJm7onHZni0L3u9FL4qP7BL9ZHAiEAttXDQpxfj28fIrFvn2dS
yspTRYbC7HVMJdie4ZQF/DoAdwAS8U40vVNyTIQGGcOPP3oT+Oe1YoeInG0wBYTr
5YYmOgAAAZLcas/5AAAEAwBIMEYCIQC63XjK4X/SiXWerD3CYZ/KEJzrgoYslCVi
ucWG6Rp55gIhAO6rSaycX/IvSGo3px4DUwBECoplVCqtjDcG0L3C1Df+MBwGA1Ud
EQQVMBOCEXBlcnVuMjIucm8udnV0LmN6MA0GCSqGSIb3DQEBDAUAA4ICAQChxwkD
J4qS3+TU0m+PsDLr2LN2fI94fuT3XSt7ChNANEbA5uBhtPcayx88rLELee9Wi/ME
292aRF6/zjeU8Nn1SXL5JNxDBDew7C3bR614r6qhF6ppimH8jHHSfTenVjsf+b0S
SYj+tejfoa7nx1xe3xAPk1mC98RF5sLrHUP7NRNqmcm3TA9hWBEkX2YBZsR+4BOI
xs+aeh0xgaJfj+GIjqnNpR1SNKA8QPnA1DM93EStZmHwzQvdhQGD3wAF8aCGvBZo
KqEk2P2ZLIZBUUao9bQdZ0CFxSVitwL9+8gOS7pENgucme9ZhsP3HbCKpkVqg9Pl
3Sate8oAGCCV5770/cu1gBt+BDOy7NdcJO8YG+m2xjhOFBNaYAV2AF6vr1LI4IDy
EQdUmTPpaw5MdOejoCHBiwaHthXSn1UNHcSwwX33TuxuDUbbAVzmIOZ4vvHe2cyz
JQpUQSya+fYLHRgLKnmH+fstAXYhJWGTxKiL3Ie1nCT2aVXUaMIpv6cTmvSSGhGX
D/H2wDXD+YWaNj4PFzQ5pNyXokz+7xnME2VCFur3O7aqLCtKKm81U/GaxfU+sM4R
HpfldHmG7hN2t/zSGGDWqNaJXojXR8zbhItsYjbOwUBJMGYH8vkhfqsOjGI7LTgr
TpwP/ZGSHkrBRkySQjn6+SwVYCmqYUEMlQ/4hQ==</ns1:certificate>
      <ns1:rsa-public-key>MIIBIjANBgkqhkiG9w0BAQEFAAOCAQ8AMIIBCgKCAQEAvhUrFa3HyDSiLINdtnATwaK+0yDBv/ZJqPdbcp/55xX61HqyHB/NWlm6
gqCmwIFBax7J2f3hhi4nvQMxnuZx0uFvfBlGTI7S9ck0cw7rim8afsDi99+1jGxsuowVSNmhttKLN+sgGHCeUFn3MC9jXC0mDTtH
uNlMZZ6sYCcBG33C1sBRoiS3dfcnFwasK9dh+98u+bhL6gKCbaAF/6EaNeO+MNiKoIhQxTYTtCK4X1LO4UNACwmm3DOn7S3IWgWV
nY0QtnP88OGcOBAYM5dBCRzEADSQ5pnivo9epHLxcdpnkkiQNg6SgsX2Qi0QUgiErLQ2CMZs886hqzCadsKb/QIDAQAB</ns1:rsa-public-key>
    </ns1:client-credentials-in-use>
    <ns1:server-credentials-in-use>
      <ns1:rsa-public-key>MIIBIjANBgkqhkiG9w0BAQEFAAOCAQ8AMIIBCgKCAQEAvhUrFa3HyDSiLINdtnATwaK+0yDBv/ZJqPdbcp/55xX61HqyHB/NWlm6
gqCmwIFBax7J2f3hhi4nvQMxnuZx0uFvfBlGTI7S9ck0cw7rim8afsDi99+1jGxsuowVSNmhttKLN+sgGHCeUFn3MC9jXC0mDTtH
uNlMZZ6sYCcBG33C1sBRoiS3dfcnFwasK9dh+98u+bhL6gKCbaAF/6EaNeO+MNiKoIhQxTYTtCK4X1LO4UNACwmm3DOn7S3IWgWV
nY0QtnP88OGcOBAYM5dBCRzEADSQ5pnivo9epHLxcdpnkkiQNg6SgsX2Qi0QUgiErLQ2CMZs886hqzCadsKb/QIDAQAB</ns1:rsa-public-key>
    </ns1:server-credentials-in-use>
  </ns1:host>
</ns1:manifest>
